contextplt/__init__.py
contextplt/__version__.py
contextplt/main.py
contextplt-0.1.6.dist-info/METADATA
contextplt-0.1.6.dist-info/WHEEL
contextplt-0.1.6.dist-info/top_level.txt
contextplt-0.1.6.dist-info/RECORD
